setup.cfg
setup.py
imgur_cli/__init__.py
imgur_cli/cli.py
imgur_cli/cli_api.py
imgur_cli/exceptions.py
imgur_cli/utils.py
imgur_cli.egg-info/PKG-INFO
imgur_cli.egg-info/SOURCES.txt
imgur_cli.egg-info/dependency_links.txt
imgur_cli.egg-info/entry_points.txt
imgur_cli.egg-info/requires.txt
imgur_cli.egg-info/top_level.txt
tests/__init__.py
tests/test_cli.py