Metadata-Version: 1.1
Name: imgur-cli
Version: 0.0.1
Summary: Imgur CLI
Home-page: https://github.com/ueg1990/imgur-cli.git
Author: Usman Ehtesham Gul
Author-email: uehtesham90@gmail.com
License: MIT
Keywords: imgur cli imgurpython meme memes
Platform: UNKNOWN
Classifier: Development Status :: 3 - Alpha
Classifier: Intended Audience :: Developers
Classifier: Topic :: Software Development :: Build Tools
Classifier: License :: OSI Approved :: MIT License
Classifier: Programming Language :: Python :: 3.4
